punctfix/__init__.py
punctfix/inference.py
punctfix/models.py
punctfix/streaming.py
tests/__init__.py
tests/test_punctuation.py
punctfix-0.11.1.dist-info/LICENCE.txt
punctfix-0.11.1.dist-info/METADATA
punctfix-0.11.1.dist-info/WHEEL
punctfix-0.11.1.dist-info/top_level.txt
punctfix-0.11.1.dist-info/RECORD
