Metadata-Version: 2.1
Name: punctfix
Version: 0.11.1
Summary: Punctuation restoration library
Home-page: https://github.com/danspeech/punctfix
Author: Martin Carsten Nielsen
Author-email: martin@alvenir.ai
Classifier: Programming Language :: Python :: 3
Classifier: Development Status :: 5 - Production/Stable
Classifier: Operating System :: OS Independent
License-File: LICENCE.txt
Requires-Dist: tokenizers >=0.11.6
Requires-Dist: transformers >=4.13
Requires-Dist: torch
